RSA/RSA.py
RSA/__init__.py
_random/__init__.py
_random/_random.py
hsah/__init__.py
hsah/hash.py
math/__init__.py
math/math.py
mod/__init__.py
mod/mod.py
morse/__init__.py
morse/morse.py
puzzle/__init__.py
puzzle/puzzle.py
sort/__init__.py
sort/sort.py
mlymath-0.4.2.dist-info/METADATA
mlymath-0.4.2.dist-info/WHEEL
mlymath-0.4.2.dist-info/top_level.txt
mlymath-0.4.2.dist-info/RECORD
